transformers_finetuning/__init__.py
transformers_finetuning/losses.py
transformers_finetuning/model_training_utils.py
transformers_finetuning/models.py
transformers_finetuning/optimization.py
transformers_finetuning/tokenization.py
transformers_finetuning/utils.py
transformers_finetuning-0.3.7.dist-info/METADATA
transformers_finetuning-0.3.7.dist-info/WHEEL
transformers_finetuning-0.3.7.dist-info/top_level.txt
transformers_finetuning-0.3.7.dist-info/RECORD
