Metadata-Version: 2.1
Name: transformers-finetuning
Version: 0.3.7
Summary: A Package for fine tuning based on transformers
Home-page: https://github.com/Ankur3107/transformers_finetuning
Author: Ankur Singh
Author-email: ankur310794@gmail.com
License: UNKNOWN
Platform: UNKNOWN
Classifier: Programming Language :: Python :: 3
Classifier: License :: OSI Approved :: MIT License
Classifier: Operating System :: OS Independent
Requires-Dist: transformers
